aws_cdk_helloworld/__init__.py
aws_cdk_helloworld/aws_cdk_helloworld_stack.py
aws_cdk_helloworld-1.0.0.dist-info/METADATA
aws_cdk_helloworld-1.0.0.dist-info/WHEEL
aws_cdk_helloworld-1.0.0.dist-info/top_level.txt
aws_cdk_helloworld-1.0.0.dist-info/RECORD
